setup.py
lingkarannnn_33423319/__init__.py
lingkarannnn_33423319/luas.py
lingkarannnnn_33423319.egg-info/PKG-INFO
lingkarannnnn_33423319.egg-info/SOURCES.txt
lingkarannnnn_33423319.egg-info/dependency_links.txt
lingkarannnnn_33423319.egg-info/top_level.txt