Metadata-Version: 2.1
Name: lingkarannnnn_33423319
Version: 1.0
Summary: luas
Home-page: https://github.com/iqbull2244/goldenn.git
Author: iqbal
Author-email: <rafiiqbal2407@gmail.com>
License: MIT
Keywords: golden_ratio,golden
Classifier: Development Status :: 1 - Planning
